mahler/__init__.py
mahler/controller.py
mahler/engines/__init__.py
mahler/engines/playwright_/__init__.py
mahler/engines/playwright_/element.py
mahler/engines/playwright_/window.py
mahler/engines/selenium_/__init__.py
mahler/engines/selenium_/element.py
mahler/engines/selenium_/window.py
mahler/fingerprint.py
mahler/protocols/__init__.py
mahler/protocols/element.py
mahler/protocols/window.py
mahler-0.1.0.dist-info/LICENSE
mahler-0.1.0.dist-info/METADATA
mahler-0.1.0.dist-info/WHEEL
mahler-0.1.0.dist-info/RECORD
