Metadata-Version: 2.1
Name: mahler
Version: 0.1.0
Summary: Web browser automation wrapper.
Author: Michael Everingham
Author-email: 36551116+michaeleveringham@users.noreply.github.com
Requires-Python: >=3.12,<4.0
Classifier: Programming Language :: Python :: 3
Classifier: Programming Language :: Python :: 3.12
Requires-Dist: playwright (>=1.51.0,<2.0.0)
Requires-Dist: selenium (>=4.30.0,<5.0.0)
Requires-Dist: webdriver-manager (>=4.0.2,<5.0.0)
